[
{
"asset_id":
"914a4d5a-a30c-4bd3-b3e0-aa51994a109a",
"blob":
"1b953042-a749-49bb-80a2-984546fec79b",
"created":
"2024-06-05T18:58:28.558815Z",
"metadata":
{
"@context":
"https://raw.githubusercontent.com/dandi/schema/master/releases/0.6.7/context.json",
"access":
[
{
"schemaKey":
"AccessRequirements",
"status":
"dandi:OpenAccess"
}
],
"approach":
[],
"blobDateModified":
"2024-06-05T14:31:27.246508-04:00",
"contentSize":
224583316,
"contentUrl":
[
"https://api.dandiarchive.org/api/assets/914a4d5a-a30c-4bd3-b3e0-aa51994a109a/download/",
"https://dandiarchive.s3.amazonaws.com/blobs/1b9/530/1b953042-a749-49bb-80a2-984546fec79b"
],
"dateModified":
"2024-06-05T14:58:17.890918-04:00",
"digest":
{
"dandi:dandi-etag":
"eaad322a767cd54307132671f6874283-4",
"dandi:sha2-256":
"35535c2ea2827826f561ff7cfeb38f3b216eb8e8292dd4c9d7391f068e31c7ed"
},
"encodingFormat":
"application/x-nwb",
"id":
"dandiasset:914a4d5a-a30c-4bd3-b3e0-aa51994a109a",
"identifier":
"914a4d5a-a30c-4bd3-b3e0-aa51994a109a",
"measurementTechnique":
[],
"path":
"sub-Finch-z-r12r13-21-held-in-calib/sub-Finch-z-r12r13-21-held-in-calib_ses-20210626.nwb",
"schemaKey":
"Asset",
"schemaVersion":
"0.6.7",
"variableMeasured":
[],
"wasAttributedTo":
[
{
"age":
{
"schemaKey":
"PropertyValue",
"unitText":
"ISO-8601 duration",
"value":
"P90D/",
"valueReference":
{
"schemaKey":
"PropertyValue",
"value":
"dandi:BirthReference"
}
},
"identifier":
"Finch_z_r12r13_21_held_in_calib",
"schemaKey":
"Participant",
"sex":
{
"identifier":
"http://purl.obolibrary.org/obo/PATO_0000384",
"name":
"Male",
"schemaKey":
"SexType"
},
"species":
{
"identifier":
"http://purl.obolibrary.org/obo/NCBITaxon_59729",
"name":
"Taeniopygia guttata - Zebra finch",
"schemaKey":
"SpeciesType"
}
}
],
"wasGeneratedBy":
[
{
"description":
"Freely-awake-singing Zebra finch with a Neuropixels probe implanted in RA.",
"name":
"Acquisition session",
"schemaKey":
"Session",
"startDate":
"2021-06-26T00:00:00-07:00"
},
{
"description":
"Metadata generated by DANDI cli",
"endDate":
"2024-06-05T14:58:17.890824-04:00",
"id":
"urn:uuid:8f196962-a82a-433c-be94-ae2f3e5a393e",
"name":
"Metadata generation",
"schemaKey":
"Activity",
"startDate":
"2024-06-05T14:58:16.645233-04:00",
"wasAssociatedWith":
[
{
"identifier":
"RRID:SCR_019009",
"name":
"DANDI Command Line Interface",
"schemaKey":
"Software",
"url":
"https://github.com/dandi/dandi-cli",
"version":
"0.60.0"
}
]
}
]
},
"modified":
"2024-06-05T18:58:28.558828Z",
"path":
"sub-Finch-z-r12r13-21-held-in-calib/sub-Finch-z-r12r13-21-held-in-calib_ses-20210626.nwb",
"size":
224583316
},
{
"asset_id":
"68afa39f-b577-4183-a206-dde24d718b78",
"blob":
"6017e024-9549-4e8c-8e24-08cf4fb7919f",
"created":
"2024-06-05T18:58:22.382482Z",
"metadata":
{
"@context":
"https://raw.githubusercontent.com/dandi/schema/master/releases/0.6.7/context.json",
"access":
[
{
"schemaKey":
"AccessRequirements",
"status":
"dandi:OpenAccess"
}
],
"approach":
[],
"blobDateModified":
"2024-06-05T14:32:08.865922-04:00",
"contentSize":
591750268,
"contentUrl":
[
"https://api.dandiarchive.org/api/assets/68afa39f-b577-4183-a206-dde24d718b78/download/",
"https://dandiarchive.s3.amazonaws.com/blobs/601/7e0/6017e024-9549-4e8c-8e24-08cf4fb7919f"
],
"dateModified":
"2024-06-05T14:58:18.050207-04:00",
"digest":
{
"dandi:dandi-etag":
"239372f17c0086dfb74ecf691a703f1c-9",
"dandi:sha2-256":
"7474ec1158f34fb364fa5ab03c2e863ee41b6f8fa1637551bb75241ebe2f3204"
},
"encodingFormat":
"application/x-nwb",
"id":
"dandiasset:68afa39f-b577-4183-a206-dde24d718b78",
"identifier":
"68afa39f-b577-4183-a206-dde24d718b78",
"measurementTechnique":
[],
"path":
"sub-Finch-z-r12r13-21-held-in-calib/sub-Finch-z-r12r13-21-held-in-calib_ses-20210627.nwb",
"schemaKey":
"Asset",
"schemaVersion":
"0.6.7",
"variableMeasured":
[],
"wasAttributedTo":
[
{
"age":
{
"schemaKey":
"PropertyValue",
"unitText":
"ISO-8601 duration",
"value":
"P90D/",
"valueReference":
{
"schemaKey":
"PropertyValue",
"value":
"dandi:BirthReference"
}
},
"identifier":
"Finch_z_r12r13_21_held_in_calib",
"schemaKey":
"Participant",
"sex":
{
"identifier":
"http://purl.obolibrary.org/obo/PATO_0000384",
"name":
"Male",
"schemaKey":
"SexType"
},
"species":
{
"identifier":
"http://purl.obolibrary.org/obo/NCBITaxon_59729",
"name":
"Taeniopygia guttata - Zebra finch",
"schemaKey":
"SpeciesType"
}
}
],
"wasGeneratedBy":
[
{
"description":
"Freely-awake-singing Zebra finch with a Neuropixels probe implanted in RA.",
"name":
"Acquisition session",
"schemaKey":
"Session",
"startDate":
"2021-06-27T00:00:00-07:00"
},
{
"description":
"Metadata generated by DANDI cli",
"endDate":
"2024-06-05T14:58:18.050174-04:00",
"id":
"urn:uuid:3ef34268-8f63-4b2c-9d53-a8d280634c4e",
"name":
"Metadata generation",
"schemaKey":
"Activity",
"startDate":
"2024-06-05T14:58:17.993384-04:00",
"wasAssociatedWith":
[
{
"identifier":
"RRID:SCR_019009",
"name":
"DANDI Command Line Interface",
"schemaKey":
"Software",
"url":
"https://github.com/dandi/dandi-cli",
"version":
"0.60.0"
}
]
}
]
},
"modified":
"2024-06-05T18:58:22.382496Z",
"path":
"sub-Finch-z-r12r13-21-held-in-calib/sub-Finch-z-r12r13-21-held-in-calib_ses-20210627.nwb",
"size":
591750268
},
{
"asset_id":
"8a239242-2b86-4c15-8afd-6c737a8a3cca",
"blob":
"403d055b-b6d7-4671-afd3-1cc31cfd5a0e",
"created":
"2024-06-05T18:58:19.470337Z",
"metadata":
{
"@context":
"https://raw.githubusercontent.com/dandi/schema/master/releases/0.6.7/context.json",
"access":
[
{
"schemaKey":
"AccessRequirements",
"status":
"dandi:OpenAccess"
}
],
"approach":
[],
"blobDateModified":
"2024-06-05T14:32:20.532758-04:00",
"contentSize":
163388824,
"contentUrl":
[
"https://api.dandiarchive.org/api/assets/8a239242-2b86-4c15-8afd-6c737a8a3cca/download/",
"https://dandiarchive.s3.amazonaws.com/blobs/403/d05/403d055b-b6d7-4671-afd3-1cc31cfd5a0e"
],
"dateModified":
"2024-06-05T14:58:16.919173-04:00",
"digest":
{
"dandi:dandi-etag":
"6cfc0dbada08acc4e57cadbc26468d92-3",
"dandi:sha2-256":
"2c356aa27ce8551670ffd68ff0482b6dcd61b46fad27434bb4b7224f16947124"
},
"encodingFormat":
"application/x-nwb",
"id":
"dandiasset:8a239242-2b86-4c15-8afd-6c737a8a3cca",
"identifier":
"8a239242-2b86-4c15-8afd-6c737a8a3cca",
"measurementTechnique":
[],
"path":
"sub-Finch-z-r12r13-21-held-in-calib/sub-Finch-z-r12r13-21-held-in-calib_ses-20210628.nwb",
"schemaKey":
"Asset",
"schemaVersion":
"0.6.7",
"variableMeasured":
[],
"wasAttributedTo":
[
{
"age":
{
"schemaKey":
"PropertyValue",
"unitText":
"ISO-8601 duration",
"value":
"P90D/",
"valueReference":
{
"schemaKey":
"PropertyValue",
"value":
"dandi:BirthReference"
}
},
"identifier":
"Finch_z_r12r13_21_held_in_calib",
"schemaKey":
"Participant",
"sex":
{
"identifier":
"http://purl.obolibrary.org/obo/PATO_0000384",
"name":
"Male",
"schemaKey":
"SexType"
},
"species":
{
"identifier":
"http://purl.obolibrary.org/obo/NCBITaxon_59729",
"name":
"Taeniopygia guttata - Zebra finch",
"schemaKey":
"SpeciesType"
}
}
],
"wasGeneratedBy":
[
{
"description":
"Freely-awake-singing Zebra finch with a Neuropixels probe implanted in RA.",
"name":
"Acquisition session",
"schemaKey":
"Session",
"startDate":
"2021-06-28T00:00:00-07:00"
},
{
"description":
"Metadata generated by DANDI cli",
"endDate":
"2024-06-05T14:58:16.919126-04:00",
"id":
"urn:uuid:f7ae5764-9d16-44b9-9f0b-446c0dd2aa36",
"name":
"Metadata generation",
"schemaKey":
"Activity",
"startDate":
"2024-06-05T14:58:16.211066-04:00",
"wasAssociatedWith":
[
{
"identifier":
"RRID:SCR_019009",
"name":
"DANDI Command Line Interface",
"schemaKey":
"Software",
"url":
"https://github.com/dandi/dandi-cli",
"version":
"0.60.0"
}
]
}
]
},
"modified":
"2024-06-05T18:58:19.470350Z",
"path":
"sub-Finch-z-r12r13-21-held-in-calib/sub-Finch-z-r12r13-21-held-in-calib_ses-20210628.nwb",
"size":
163388824
},
{
"asset_id":
"43119082-43c0-4dee-a6c7-63c5ff71a819",
"blob":
"f1d09856-4205-4cdf-bda0-1d2ec97fcfba",
"created":
"2024-06-05T18:58:17.433723Z",
"metadata":
{
"@context":
"https://raw.githubusercontent.com/dandi/schema/master/releases/0.6.7/context.json",
"access":
[
{
"schemaKey":
"AccessRequirements",
"status":
"dandi:OpenAccess"
}
],
"approach":
[],
"blobDateModified":
"2024-06-05T14:33:07.443098-04:00",
"contentSize":
40999840,
"contentUrl":
[
"https://api.dandiarchive.org/api/assets/43119082-43c0-4dee-a6c7-63c5ff71a819/download/",
"https://dandiarchive.s3.amazonaws.com/blobs/f1d/098/f1d09856-4205-4cdf-bda0-1d2ec97fcfba"
],
"dateModified":
"2024-06-05T14:58:16.835245-04:00",
"digest":
{
"dandi:dandi-etag":
"d76de04046c51a87e8965671ccb1a598-1",
"dandi:sha2-256":
"dadcb12db523336b6ddfe89ea06b06d2490d3d0811b898088121852d94e42e97"
},
"encodingFormat":
"application/x-nwb",
"id":
"dandiasset:43119082-43c0-4dee-a6c7-63c5ff71a819",
"identifier":
"43119082-43c0-4dee-a6c7-63c5ff71a819",
"measurementTechnique":
[],
"path":
"sub-Finch-z-r12r13-21-held-in-minival/sub-Finch-z-r12r13-21-held-in-minival_ses-20210626.nwb",
"schemaKey":
"Asset",
"schemaVersion":
"0.6.7",
"variableMeasured":
[],
"wasAttributedTo":
[
{
"age":
{
"schemaKey":
"PropertyValue",
"unitText":
"ISO-8601 duration",
"value":
"P90D/",
"valueReference":
{
"schemaKey":
"PropertyValue",
"value":
"dandi:BirthReference"
}
},
"identifier":
"Finch_z_r12r13_21_held_in_minival",
"schemaKey":
"Participant",
"sex":
{
"identifier":
"http://purl.obolibrary.org/obo/PATO_0000384",
"name":
"Male",
"schemaKey":
"SexType"
},
"species":
{
"identifier":
"http://purl.obolibrary.org/obo/NCBITaxon_59729",
"name":
"Taeniopygia guttata - Zebra finch",
"schemaKey":
"SpeciesType"
}
}
],
"wasGeneratedBy":
[
{
"description":
"Freely-awake-singing Zebra finch with a Neuropixels probe implanted in RA.",
"name":
"Acquisition session",
"schemaKey":
"Session",
"startDate":
"2021-06-26T00:00:00-07:00"
},
{
"description":
"Metadata generated by DANDI cli",
"endDate":
"2024-06-05T14:58:16.835199-04:00",
"id":
"urn:uuid:63236210-8379-4d59-8031-9413da4e24fa",
"name":
"Metadata generation",
"schemaKey":
"Activity",
"startDate":
"2024-06-05T14:58:16.047168-04:00",
"wasAssociatedWith":
[
{
"identifier":
"RRID:SCR_019009",
"name":
"DANDI Command Line Interface",
"schemaKey":
"Software",
"url":
"https://github.com/dandi/dandi-cli",
"version":
"0.60.0"
}
]
}
]
},
"modified":
"2024-06-05T18:58:17.433736Z",
"path":
"sub-Finch-z-r12r13-21-held-in-minival/sub-Finch-z-r12r13-21-held-in-minival_ses-20210626.nwb",
"size":
40999840
},
{
"asset_id":
"9e3ece2b-08d3-460e-974b-10a2d54fad0b",
"blob":
"be6a96b0-adfd-4c1d-aed5-df00125ea2f4",
"created":
"2024-06-05T18:58:19.088647Z",
"metadata":
{
"@context":
"https://raw.githubusercontent.com/dandi/schema/master/releases/0.6.7/context.json",
"access":
[
{
"schemaKey":
"AccessRequirements",
"status":
"dandi:OpenAccess"
}
],
"approach":
[],
"blobDateModified":
"2024-06-05T14:33:10.226059-04:00",
"contentSize":
40999840,
"contentUrl":
[
"https://api.dandiarchive.org/api/assets/9e3ece2b-08d3-460e-974b-10a2d54fad0b/download/",
"https://dandiarchive.s3.amazonaws.com/blobs/be6/a96/be6a96b0-adfd-4c1d-aed5-df00125ea2f4"
],
"dateModified":
"2024-06-05T14:58:16.812781-04:00",
"digest":
{
"dandi:dandi-etag":
"bb91719b66c6ab843bd446652f07120b-1",
"dandi:sha2-256":
"15b26f9ae3771519dca0c3cd9c0ab295409ffb24ba121af85cd72666c99e15f4"
},
"encodingFormat":
"application/x-nwb",
"id":
"dandiasset:9e3ece2b-08d3-460e-974b-10a2d54fad0b",
"identifier":
"9e3ece2b-08d3-460e-974b-10a2d54fad0b",
"measurementTechnique":
[],
"path":
"sub-Finch-z-r12r13-21-held-in-minival/sub-Finch-z-r12r13-21-held-in-minival_ses-20210627.nwb",
"schemaKey":
"Asset",
"schemaVersion":
"0.6.7",
"variableMeasured":
[],
"wasAttributedTo":
[
{
"age":
{
"schemaKey":
"PropertyValue",
"unitText":
"ISO-8601 duration",
"value":
"P90D/",
"valueReference":
{
"schemaKey":
"PropertyValue",
"value":
"dandi:BirthReference"
}
},
"identifier":
"Finch_z_r12r13_21_held_in_minival",
"schemaKey":
"Participant",
"sex":
{
"identifier":
"http://purl.obolibrary.org/obo/PATO_0000384",
"name":
"Male",
"schemaKey":
"SexType"
},
"species":
{
"identifier":
"http://purl.obolibrary.org/obo/NCBITaxon_59729",
"name":
"Taeniopygia guttata - Zebra finch",
"schemaKey":
"SpeciesType"
}
}
],
"wasGeneratedBy":
[
{
"description":
"Freely-awake-singing Zebra finch with a Neuropixels probe implanted in RA.",
"name":
"Acquisition session",
"schemaKey":
"Session",
"startDate":
"2021-06-27T00:00:00-07:00"
},
{
"description":
"Metadata generated by DANDI cli",
"endDate":
"2024-06-05T14:58:16.812718-04:00",
"id":
"urn:uuid:2ed77be5-84e5-4e52-8157-a611faea8e8f",
"name":
"Metadata generation",
"schemaKey":
"Activity",
"startDate":
"2024-06-05T14:58:15.939476-04:00",
"wasAssociatedWith":
[
{
"identifier":
"RRID:SCR_019009",
"name":
"DANDI Command Line Interface",
"schemaKey":
"Software",
"url":
"https://github.com/dandi/dandi-cli",
"version":
"0.60.0"
}
]
}
]
},
"modified":
"2024-06-05T18:58:19.088661Z",
"path":
"sub-Finch-z-r12r13-21-held-in-minival/sub-Finch-z-r12r13-21-held-in-minival_ses-20210627.nwb",
"size":
40999840
},
{
"asset_id":
"c6f02424-4bdd-4f62-8cf2-1f1897e3e672",
"blob":
"750c941b-2a88-4c74-b904-0a4c5cb1329d",
"created":
"2024-06-05T18:58:19.984356Z",
"metadata":
{
"@context":
"https://raw.githubusercontent.com/dandi/schema/master/releases/0.6.7/context.json",
"access":
[
{
"schemaKey":
"AccessRequirements",
"status":
"dandi:OpenAccess"
}
],
"approach":
[],
"blobDateModified":
"2024-06-05T14:33:13.207017-04:00",
"contentSize":
40999840,
"contentUrl":
[
"https://api.dandiarchive.org/api/assets/c6f02424-4bdd-4f62-8cf2-1f1897e3e672/download/",
"https://dandiarchive.s3.amazonaws.com/blobs/750/c94/750c941b-2a88-4c74-b904-0a4c5cb1329d"
],
"dateModified":
"2024-06-05T14:58:18.299732-04:00",
"digest":
{
"dandi:dandi-etag":
"c1445301cdec04fa84385aa4c2563625-1",
"dandi:sha2-256":
"996ee714ecc031aa3a4c4d2cbc975cb6db5ddfed18a118f2b6950f4fbae9ac2d"
},
"encodingFormat":
"application/x-nwb",
"id":
"dandiasset:c6f02424-4bdd-4f62-8cf2-1f1897e3e672",
"identifier":
"c6f02424-4bdd-4f62-8cf2-1f1897e3e672",
"measurementTechnique":
[],
"path":
"sub-Finch-z-r12r13-21-held-in-minival/sub-Finch-z-r12r13-21-held-in-minival_ses-20210628.nwb",
"schemaKey":
"Asset",
"schemaVersion":
"0.6.7",
"variableMeasured":
[],
"wasAttributedTo":
[
{
"age":
{
"schemaKey":
"PropertyValue",
"unitText":
"ISO-8601 duration",
"value":
"P90D/",
"valueReference":
{
"schemaKey":
"PropertyValue",
"value":
"dandi:BirthReference"
}
},
"identifier":
"Finch_z_r12r13_21_held_in_minival",
"schemaKey":
"Participant",
"sex":
{
"identifier":
"http://purl.obolibrary.org/obo/PATO_0000384",
"name":
"Male",
"schemaKey":
"SexType"
},
"species":
{
"identifier":
"http://purl.obolibrary.org/obo/NCBITaxon_59729",
"name":
"Taeniopygia guttata - Zebra finch",
"schemaKey":
"SpeciesType"
}
}
],
"wasGeneratedBy":
[
{
"description":
"Freely-awake-singing Zebra finch with a Neuropixels probe implanted in RA.",
"name":
"Acquisition session",
"schemaKey":
"Session",
"startDate":
"2021-06-28T00:00:00-07:00"
},
{
"description":
"Metadata generated by DANDI cli",
"endDate":
"2024-06-05T14:58:18.299707-04:00",
"id":
"urn:uuid:312206ac-fc44-4503-b420-eb0c32475a28",
"name":
"Metadata generation",
"schemaKey":
"Activity",
"startDate":
"2024-06-05T14:58:18.295242-04:00",
"wasAssociatedWith":
[
{
"identifier":
"RRID:SCR_019009",
"name":
"DANDI Command Line Interface",
"schemaKey":
"Software",
"url":
"https://github.com/dandi/dandi-cli",
"version":
"0.60.0"
}
]
}
]
},
"modified":
"2024-06-05T18:58:19.984376Z",
"path":
"sub-Finch-z-r12r13-21-held-in-minival/sub-Finch-z-r12r13-21-held-in-minival_ses-20210628.nwb",
"size":
40999840
},
{
"asset_id":
"0aed33b3-1b0f-43c1-afff-62db907ffcc8",
"blob":
"b4f7e459-7643-4ac7-8bb0-874da1422651",
"created":
"2024-06-05T18:58:22.517003Z",
"metadata":
{
"@context":
"https://raw.githubusercontent.com/dandi/schema/master/releases/0.6.7/context.json",
"access":
[
{
"schemaKey":
"AccessRequirements",
"status":
"dandi:OpenAccess"
}
],
"approach":
[],
"blobDateModified":
"2024-06-05T14:33:17.862952-04:00",
"contentSize":
61398004,
"contentUrl":
[
"https://api.dandiarchive.org/api/assets/0aed33b3-1b0f-43c1-afff-62db907ffcc8/download/",
"https://dandiarchive.s3.amazonaws.com/blobs/b4f/7e4/b4f7e459-7643-4ac7-8bb0-874da1422651"
],
"dateModified":
"2024-06-05T14:58:20.678170-04:00",
"digest":
{
"dandi:dandi-etag":
"170f3d21f81d4ad2b00635c4eb9a5964-1",
"dandi:sha2-256":
"ce05975b77ad202893582af0b1f11ab9c8a069f6d673d8e03e69f9dc6a200bcc"
},
"encodingFormat":
"application/x-nwb",
"id":
"dandiasset:0aed33b3-1b0f-43c1-afff-62db907ffcc8",
"identifier":
"0aed33b3-1b0f-43c1-afff-62db907ffcc8",
"measurementTechnique":
[],
"path":
"sub-Finch-z-r12r13-21-held-out-calib/sub-Finch-z-r12r13-21-held-out-calib_ses-20210630.nwb",
"schemaKey":
"Asset",
"schemaVersion":
"0.6.7",
"variableMeasured":
[],
"wasAttributedTo":
[
{
"age":
{
"schemaKey":
"PropertyValue",
"unitText":
"ISO-8601 duration",
"value":
"P90D/",
"valueReference":
{
"schemaKey":
"PropertyValue",
"value":
"dandi:BirthReference"
}
},
"identifier":
"Finch_z_r12r13_21_held_out_calib",
"schemaKey":
"Participant",
"sex":
{
"identifier":
"http://purl.obolibrary.org/obo/PATO_0000384",
"name":
"Male",
"schemaKey":
"SexType"
},
"species":
{
"identifier":
"http://purl.obolibrary.org/obo/NCBITaxon_59729",
"name":
"Taeniopygia guttata - Zebra finch",
"schemaKey":
"SpeciesType"
}
}
],
"wasGeneratedBy":
[
{
"description":
"Freely-awake-singing Zebra finch with a Neuropixels probe implanted in RA.",
"name":
"Acquisition session",
"schemaKey":
"Session",
"startDate":
"2021-06-30T00:00:00-07:00"
},
{
"description":
"Metadata generated by DANDI cli",
"endDate":
"2024-06-05T14:58:20.678116-04:00",
"id":
"urn:uuid:70af6375-7895-4407-b5fb-12ed03713b75",
"name":
"Metadata generation",
"schemaKey":
"Activity",
"startDate":
"2024-06-05T14:58:20.664495-04:00",
"wasAssociatedWith":
[
{
"identifier":
"RRID:SCR_019009",
"name":
"DANDI Command Line Interface",
"schemaKey":
"Software",
"url":
"https://github.com/dandi/dandi-cli",
"version":
"0.60.0"
}
]
}
]
},
"modified":
"2024-06-05T18:58:22.517021Z",
"path":
"sub-Finch-z-r12r13-21-held-out-calib/sub-Finch-z-r12r13-21-held-out-calib_ses-20210630.nwb",
"size":
61398004
},
{
"asset_id":
"17130548-235b-4631-95b2-000af0c3eb25",
"blob":
"eb4441ed-b344-4171-9204-03574a73c179",
"created":
"2024-06-05T18:58:23.451898Z",
"metadata":
{
"@context":
"https://raw.githubusercontent.com/dandi/schema/master/releases/0.6.7/context.json",
"access":
[
{
"schemaKey":
"AccessRequirements",
"status":
"dandi:OpenAccess"
}
],
"approach":
[],
"blobDateModified":
"2024-06-05T14:33:22.396888-04:00",
"contentSize":
61398004,
"contentUrl":
[
"https://api.dandiarchive.org/api/assets/17130548-235b-4631-95b2-000af0c3eb25/download/",
"https://dandiarchive.s3.amazonaws.com/blobs/eb4/441/eb4441ed-b344-4171-9204-03574a73c179"
],
"dateModified":
"2024-06-05T14:58:21.450899-04:00",
"digest":
{
"dandi:dandi-etag":
"3695ba99c25205b5f1fbf5a2668bf3bd-1",
"dandi:sha2-256":
"7a762a8d3334822ac764a9400925c6445b36c5ddff37c080adaf0c321591aa3d"
},
"encodingFormat":
"application/x-nwb",
"id":
"dandiasset:17130548-235b-4631-95b2-000af0c3eb25",
"identifier":
"17130548-235b-4631-95b2-000af0c3eb25",
"measurementTechnique":
[],
"path":
"sub-Finch-z-r12r13-21-held-out-calib/sub-Finch-z-r12r13-21-held-out-calib_ses-20210701.nwb",
"schemaKey":
"Asset",
"schemaVersion":
"0.6.7",
"variableMeasured":
[],
"wasAttributedTo":
[
{
"age":
{
"schemaKey":
"PropertyValue",
"unitText":
"ISO-8601 duration",
"value":
"P90D/",
"valueReference":
{
"schemaKey":
"PropertyValue",
"value":
"dandi:BirthReference"
}
},
"identifier":
"Finch_z_r12r13_21_held_out_calib",
"schemaKey":
"Participant",
"sex":
{
"identifier":
"http://purl.obolibrary.org/obo/PATO_0000384",
"name":
"Male",
"schemaKey":
"SexType"
},
"species":
{
"identifier":
"http://purl.obolibrary.org/obo/NCBITaxon_59729",
"name":
"Taeniopygia guttata - Zebra finch",
"schemaKey":
"SpeciesType"
}
}
],
"wasGeneratedBy":
[
{
"description":
"Freely-awake-singing Zebra finch with a Neuropixels probe implanted in RA.",
"name":
"Acquisition session",
"schemaKey":
"Session",
"startDate":
"2021-07-01T00:00:00-07:00"
},
{
"description":
"Metadata generated by DANDI cli",
"endDate":
"2024-06-05T14:58:21.450873-04:00",
"id":
"urn:uuid:6bd514c8-230f-4569-a547-f4d120303faa",
"name":
"Metadata generation",
"schemaKey":
"Activity",
"startDate":
"2024-06-05T14:58:21.448464-04:00",
"wasAssociatedWith":
[
{
"identifier":
"RRID:SCR_019009",
"name":
"DANDI Command Line Interface",
"schemaKey":
"Software",
"url":
"https://github.com/dandi/dandi-cli",
"version":
"0.60.0"
}
]
}
]
},
"modified":
"2024-06-05T18:58:23.451916Z",
"path":
"sub-Finch-z-r12r13-21-held-out-calib/sub-Finch-z-r12r13-21-held-out-calib_ses-20210701.nwb",
"size":
61398004
},
{
"asset_id":
"04de4f52-21fa-4789-9e19-92a480f62518",
"blob":
"e9b34da5-2e41-40bb-9f68-719bb5402620",
"created":
"2024-06-05T18:58:23.868521Z",
"metadata":
{
"@context":
"https://raw.githubusercontent.com/dandi/schema/master/releases/0.6.7/context.json",
"access":
[
{
"schemaKey":
"AccessRequirements",
"status":
"dandi:OpenAccess"
}
],
"approach":
[],
"blobDateModified":
"2024-06-05T14:33:26.652828-04:00",
"contentSize":
61398004,
"contentUrl":
[
"https://api.dandiarchive.org/api/assets/04de4f52-21fa-4789-9e19-92a480f62518/download/",
"https://dandiarchive.s3.amazonaws.com/blobs/e9b/34d/e9b34da5-2e41-40bb-9f68-719bb5402620"
],
"dateModified":
"2024-06-05T14:58:21.706906-04:00",
"digest":
{
"dandi:dandi-etag":
"599ed1fe6852c67832d8ad0913a0ada8-1",
"dandi:sha2-256":
"e587fd2bb081673ea4d51899da52471855c459a5546a7d4af32aa0be933583b9"
},
"encodingFormat":
"application/x-nwb",
"id":
"dandiasset:04de4f52-21fa-4789-9e19-92a480f62518",
"identifier":
"04de4f52-21fa-4789-9e19-92a480f62518",
"measurementTechnique":
[],
"path":
"sub-Finch-z-r12r13-21-held-out-calib/sub-Finch-z-r12r13-21-held-out-calib_ses-20210705.nwb",
"schemaKey":
"Asset",
"schemaVersion":
"0.6.7",
"variableMeasured":
[],
"wasAttributedTo":
[
{
"age":
{
"schemaKey":
"PropertyValue",
"unitText":
"ISO-8601 duration",
"value":
"P90D/",
"valueReference":
{
"schemaKey":
"PropertyValue",
"value":
"dandi:BirthReference"
}
},
"identifier":
"Finch_z_r12r13_21_held_out_calib",
"schemaKey":
"Participant",
"sex":
{
"identifier":
"http://purl.obolibrary.org/obo/PATO_0000384",
"name":
"Male",
"schemaKey":
"SexType"
},
"species":
{
"identifier":
"http://purl.obolibrary.org/obo/NCBITaxon_59729",
"name":
"Taeniopygia guttata - Zebra finch",
"schemaKey":
"SpeciesType"
}
}
],
"wasGeneratedBy":
[
{
"description":
"Freely-awake-singing Zebra finch with a Neuropixels probe implanted in RA.",
"name":
"Acquisition session",
"schemaKey":
"Session",
"startDate":
"2021-07-05T00:00:00-07:00"
},
{
"description":
"Metadata generated by DANDI cli",
"endDate":
"2024-06-05T14:58:21.706888-04:00",
"id":
"urn:uuid:85185c12-df1d-41a7-beed-4f6a190b19d8",
"name":
"Metadata generation",
"schemaKey":
"Activity",
"startDate":
"2024-06-05T14:58:21.704316-04:00",
"wasAssociatedWith":
[
{
"identifier":
"RRID:SCR_019009",
"name":
"DANDI Command Line Interface",
"schemaKey":
"Software",
"url":
"https://github.com/dandi/dandi-cli",
"version":
"0.60.0"
}
]
}
]
},
"modified":
"2024-06-05T18:58:23.868534Z",
"path":
"sub-Finch-z-r12r13-21-held-out-calib/sub-Finch-z-r12r13-21-held-out-calib_ses-20210705.nwb",
"size":
61398004
}
]